color_wizard/__init__.py
color_wizard/__version__.py
color_wizard-0.0.0.dist-info/METADATA
color_wizard-0.0.0.dist-info/WHEEL
color_wizard-0.0.0.dist-info/top_level.txt
color_wizard-0.0.0.dist-info/RECORD
