Metadata-Version: 2.1
Name: color_wizard
Version: 0.0.0
Summary: Color palette wizard.
Home-page: https://github.com/mvinyard/color_wizard
Author: Michael E. Vinyard
Author-email: mvinyard.ai@gmail.com
License: MIT
Classifier: Development Status :: 2 - Pre-Alpha
Classifier: Programming Language :: Python :: 3.9
Classifier: Intended Audience :: Science/Research
Classifier: Topic :: Software Development :: Build Tools
Requires-Python: >3.9.0
